{
  "fetched_at": "2026-05-29T06:58:51.528600",
  "source": "https://elron.ee/map_data.json",
  "count": 19,
  "trains": [
    {
      "reis": "10",
      "liin": "Tallinn - Tartu",
      "reisi_algus_aeg": "08:30",
      "reisi_lopp_aeg": "10:38",
      "kiirus": "118",
      "latitude": "58.927139",
      "longitude": "26.259995",
      "rongi_suund": "151",
      "erinevus_plaanist": "",
      "lisateade": "",
      "pohjus_teade": "",
      "avalda_kodulehel": "",
      "asukoha_uuendus": "2026-05-29 09:58:50",
      "reisi_staatus": "plaaniline",
      "viimane_peatus": "Tamsalu"
    },
    {
      "reis": "13",
      "liin": "Riia / Valga - Tallinn",
      "reisi_algus_aeg": "09:40",
      "reisi_lopp_aeg": "13:18",
      "kiirus": "45",
      "latitude": "57.942083",
      "longitude": "26.236575",
      "rongi_suund": "16",
      "erinevus_plaanist": "",
      "lisateade": "",
      "pohjus_teade": "",
      "avalda_kodulehel": "",
      "asukoha_uuendus": "2026-05-29 09:58:49",
      "reisi_staatus": "plaaniline",
      "viimane_peatus": "Sangaste"
    },
    {
      "reis": "20",
      "liin": "Tallinn - Narva",
      "reisi_algus_aeg": "09:55",
      "reisi_lopp_aeg": "12:36",
      "kiirus": "34",
      "latitude": "59.421453",
      "longitude": "24.735625",
      "rongi_suund": "124",
      "erinevus_plaanist": "",
      "lisateade": "",
      "pohjus_teade": "",
      "avalda_kodulehel": "",
      "asukoha_uuendus": "2026-05-29 09:58:49",
      "reisi_staatus": "plaaniline",
      "viimane_peatus": "Tallinn"
    },
    {
      "reis": "21",
      "liin": "Narva - Tallinn",
      "reisi_algus_aeg": "09:55",
      "reisi_lopp_aeg": "12:25",
      "kiirus": "59",
      "latitude": "59.371962",
      "longitude": "28.156463",
      "rongi_suund": "266",
      "erinevus_plaanist": "",
      "lisateade": "",
      "pohjus_teade": "",
      "avalda_kodulehel": "",
      "asukoha_uuendus": "2026-05-29 09:58:49",
      "reisi_staatus": "plaaniline",
      "viimane_peatus": "Narva"
    },
    {
      "reis": "223",
      "liin": "Narva - Tallinn",
      "reisi_algus_aeg": "07:00",
      "reisi_lopp_aeg": "10:09",
      "kiirus": "44",
      "latitude": "59.423559",
      "longitude": "24.805233",
      "rongi_suund": "273",
      "erinevus_plaanist": "",
      "lisateade": "",
      "pohjus_teade": "",
      "avalda_kodulehel": "",
      "asukoha_uuendus": "2026-05-29 09:58:49",
      "reisi_staatus": "plaaniline",
      "viimane_peatus": "Lagedi"
    },
    {
      "reis": "32",
      "liin": "Viljandi - Tallinn",
      "reisi_algus_aeg": "10:03",
      "reisi_lopp_aeg": "12:06",
      "kiirus": "0",
      "latitude": "58.357646",
      "longitude": "25.573843",
      "rongi_suund": "206",
      "erinevus_plaanist": "",
      "lisateade": "",
      "pohjus_teade": "",
      "avalda_kodulehel": "",
      "asukoha_uuendus": "2026-05-29 09:58:50",
      "reisi_staatus": "plaaniline",
      "viimane_peatus": "Viljandi"
    },
    {
      "reis": "326",
      "liin": "Rapla - Tallinn",
      "reisi_algus_aeg": "10:12",
      "reisi_lopp_aeg": "11:11",
      "kiirus": "0",
      "latitude": "58.993850",
      "longitude": "24.832722",
      "rongi_suund": "",
      "erinevus_plaanist": "",
      "lisateade": "",
      "pohjus_teade": "",
      "avalda_kodulehel": "",
      "asukoha_uuendus": "2026-05-29 09:58:49",
      "reisi_staatus": "plaaniline",
      "viimane_peatus": "Rapla"
    },
    {
      "reis": "33",
      "liin": "Tallinn - Viljandi",
      "reisi_algus_aeg": "09:59",
      "reisi_lopp_aeg": "12:05",
      "kiirus": "0",
      "latitude": "59.439398",
      "longitude": "24.735218",
      "rongi_suund": "58",
      "erinevus_plaanist": "",
      "lisateade": "",
      "pohjus_teade": "",
      "avalda_kodulehel": "",
      "asukoha_uuendus": "2026-05-29 09:58:49",
      "reisi_staatus": "plaaniline",
      "viimane_peatus": "Tallinn"
    },
    {
      "reis": "442",
      "liin": "Tallinn - Tapa",
      "reisi_algus_aeg": "09:03",
      "reisi_lopp_aeg": "10:19",
      "kiirus": "90",
      "latitude": "59.288241",
      "longitude": "25.603724",
      "rongi_suund": "108",
      "erinevus_plaanist": "",
      "lisateade": "",
      "pohjus_teade": "",
      "avalda_kodulehel": "",
      "asukoha_uuendus": "2026-05-29 09:58:51",
      "reisi_staatus": "plaaniline",
      "viimane_peatus": "Mustjõe"
    },
    {
      "reis": "469",
      "liin": "Aegviidu - Tallinn",
      "reisi_algus_aeg": "09:45",
      "reisi_lopp_aeg": "10:40",
      "kiirus": "0",
      "latitude": "59.337006",
      "longitude": "25.334661",
      "rongi_suund": "303",
      "erinevus_plaanist": "",
      "lisateade": "",
      "pohjus_teade": "",
      "avalda_kodulehel": "",
      "asukoha_uuendus": "2026-05-29 09:58:49",
      "reisi_staatus": "plaaniline",
      "viimane_peatus": "Kehra"
    },
    {
      "reis": "548",
      "liin": "Paldiski - Tallinn",
      "reisi_algus_aeg": "10:00",
      "reisi_lopp_aeg": "10:54",
      "kiirus": "0",
      "latitude": "59.344006",
      "longitude": "24.061396",
      "rongi_suund": "316",
      "erinevus_plaanist": "",
      "lisateade": "",
      "pohjus_teade": "",
      "avalda_kodulehel": "",
      "asukoha_uuendus": "2026-05-29 09:58:50",
      "reisi_staatus": "plaaniline",
      "viimane_peatus": "Paldiski"
    },
    {
      "reis": "549",
      "liin": "Tallinn - Paldiski",
      "reisi_algus_aeg": "09:45",
      "reisi_lopp_aeg": "10:39",
      "kiirus": "69",
      "latitude": "59.385245",
      "longitude": "24.680722",
      "rongi_suund": "253",
      "erinevus_plaanist": "",
      "lisateade": "",
      "pohjus_teade": "",
      "avalda_kodulehel": "",
      "asukoha_uuendus": "2026-05-29 09:58:50",
      "reisi_staatus": "plaaniline",
      "viimane_peatus": "Nõmme"
    },
    {
      "reis": "645",
      "liin": "Tallinn - Turba",
      "reisi_algus_aeg": "09:05",
      "reisi_lopp_aeg": "10:08",
      "kiirus": "111",
      "latitude": "59.170377",
      "longitude": "24.319190",
      "rongi_suund": "184",
      "erinevus_plaanist": "1",
      "lisateade": "",
      "pohjus_teade": "",
      "avalda_kodulehel": "",
      "asukoha_uuendus": "2026-05-29 09:58:50",
      "reisi_staatus": "plaaniline",
      "viimane_peatus": "Laitse"
    },
    {
      "reis": "646",
      "liin": "Turba - Tallinn",
      "reisi_algus_aeg": "09:32",
      "reisi_lopp_aeg": "10:34",
      "kiirus": "68",
      "latitude": "59.306075",
      "longitude": "24.408953",
      "rongi_suund": "89",
      "erinevus_plaanist": "",
      "lisateade": "",
      "pohjus_teade": "",
      "avalda_kodulehel": "",
      "asukoha_uuendus": "2026-05-29 09:58:50",
      "reisi_staatus": "plaaniline",
      "viimane_peatus": "Kulna"
    },
    {
      "reis": "647",
      "liin": "Tallinn - Turba",
      "reisi_algus_aeg": "10:05",
      "reisi_lopp_aeg": "11:07",
      "kiirus": "0",
      "latitude": "59.440370",
      "longitude": "24.736203",
      "rongi_suund": "",
      "erinevus_plaanist": "",
      "lisateade": "",
      "pohjus_teade": "",
      "avalda_kodulehel": "",
      "asukoha_uuendus": "2026-05-29 09:58:49",
      "reisi_staatus": "plaaniline",
      "viimane_peatus": "Tallinn"
    },
    {
      "reis": "747",
      "liin": "Tallinn - Keila",
      "reisi_algus_aeg": "09:25",
      "reisi_lopp_aeg": "09:59",
      "kiirus": "23",
      "latitude": "59.306054",
      "longitude": "24.416716",
      "rongi_suund": "269",
      "erinevus_plaanist": "",
      "lisateade": "",
      "pohjus_teade": "",
      "avalda_kodulehel": "",
      "asukoha_uuendus": "2026-05-29 09:58:49",
      "reisi_staatus": "plaaniline",
      "viimane_peatus": "Valingu"
    },
    {
      "reis": "748",
      "liin": "Keila - Tallinn",
      "reisi_algus_aeg": "09:40",
      "reisi_lopp_aeg": "10:14",
      "kiirus": "0",
      "latitude": "59.376608",
      "longitude": "24.655755",
      "rongi_suund": "45",
      "erinevus_plaanist": "",
      "lisateade": "",
      "pohjus_teade": "",
      "avalda_kodulehel": "",
      "asukoha_uuendus": "2026-05-29 09:58:51",
      "reisi_staatus": "plaaniline",
      "viimane_peatus": "Kivimäe"
    },
    {
      "reis": "90",
      "liin": "Tallinn - Tartu",
      "reisi_algus_aeg": "09:55",
      "reisi_lopp_aeg": "12:02",
      "kiirus": "34",
      "latitude": "59.421185",
      "longitude": "24.736429",
      "rongi_suund": "124",
      "erinevus_plaanist": "",
      "lisateade": "",
      "pohjus_teade": "",
      "avalda_kodulehel": "",
      "asukoha_uuendus": "2026-05-29 09:58:50",
      "reisi_staatus": "plaaniline",
      "viimane_peatus": "Tallinn"
    },
    {
      "reis": "91",
      "liin": "Tartu-Tallinn",
      "reisi_algus_aeg": "08:59",
      "reisi_lopp_aeg": "11:07",
      "kiirus": "84",
      "latitude": "59.166092",
      "longitude": "26.100840",
      "rongi_suund": "317",
      "erinevus_plaanist": "1",
      "lisateade": "",
      "pohjus_teade": "",
      "avalda_kodulehel": "",
      "asukoha_uuendus": "2026-05-29 09:58:50",
      "reisi_staatus": "plaaniline",
      "viimane_peatus": "Tamsalu"
    }
  ]
}