{
  "fetched_at": "2026-05-31T18:42:35.509077",
  "source": "https://elron.ee/map_data.json",
  "count": 15,
  "trains": [
    {
      "reis": "106",
      "liin": "Tallinn - Tartu",
      "reisi_algus_aeg": "19:55",
      "reisi_lopp_aeg": "22:28",
      "kiirus": "79",
      "latitude": "58.898356",
      "longitude": "26.287859",
      "rongi_suund": "156",
      "erinevus_plaanist": "",
      "lisateade": "",
      "pohjus_teade": "",
      "avalda_kodulehel": "",
      "asukoha_uuendus": "2026-05-31 21:42:32",
      "reisi_staatus": "plaaniline",
      "viimane_peatus": "Vägeva"
    },
    {
      "reis": "107",
      "liin": "Tartu-Tallinn",
      "reisi_algus_aeg": "21:21",
      "reisi_lopp_aeg": "23:56",
      "kiirus": "113",
      "latitude": "58.603784",
      "longitude": "26.566735",
      "rongi_suund": "355",
      "erinevus_plaanist": "2",
      "lisateade": "",
      "pohjus_teade": "",
      "avalda_kodulehel": "",
      "asukoha_uuendus": "2026-05-31 21:42:33",
      "reisi_staatus": "hilineb peatuses",
      "viimane_peatus": "Tabivere"
    },
    {
      "reis": "128",
      "liin": "Tartu - Koidula",
      "reisi_algus_aeg": "20:30",
      "reisi_lopp_aeg": "21:54",
      "kiirus": "98",
      "latitude": "57.934992",
      "longitude": "27.453699",
      "rongi_suund": "145",
      "erinevus_plaanist": "",
      "lisateade": "",
      "pohjus_teade": "",
      "avalda_kodulehel": "",
      "asukoha_uuendus": "2026-05-31 21:42:32",
      "reisi_staatus": "plaaniline",
      "viimane_peatus": "Ilumetsa"
    },
    {
      "reis": "19",
      "liin": "Tartu-Tallinn",
      "reisi_algus_aeg": "19:40",
      "reisi_lopp_aeg": "21:49",
      "kiirus": "77",
      "latitude": "59.423385",
      "longitude": "24.786393",
      "rongi_suund": "271",
      "erinevus_plaanist": "",
      "lisateade": "",
      "pohjus_teade": "",
      "avalda_kodulehel": "",
      "asukoha_uuendus": "2026-05-31 21:42:32",
      "reisi_staatus": "plaaniline",
      "viimane_peatus": "Ülemiste"
    },
    {
      "reis": "333",
      "liin": "Tallinn - Rapla",
      "reisi_algus_aeg": "21:14",
      "reisi_lopp_aeg": "22:13",
      "kiirus": "71",
      "latitude": "59.254694",
      "longitude": "24.687878",
      "rongi_suund": "177",
      "erinevus_plaanist": "",
      "lisateade": "",
      "pohjus_teade": "",
      "avalda_kodulehel": "",
      "asukoha_uuendus": "2026-05-31 21:42:33",
      "reisi_staatus": "plaaniline",
      "viimane_peatus": "Kasemetsa"
    },
    {
      "reis": "38",
      "liin": "Viljandi - Tallinn",
      "reisi_algus_aeg": "20:03",
      "reisi_lopp_aeg": "22:09",
      "kiirus": "29",
      "latitude": "59.237092",
      "longitude": "24.685474",
      "rongi_suund": "358",
      "erinevus_plaanist": "",
      "lisateade": "",
      "pohjus_teade": "",
      "avalda_kodulehel": "",
      "asukoha_uuendus": "2026-05-31 21:42:32",
      "reisi_staatus": "plaaniline",
      "viimane_peatus": "Kohila"
    },
    {
      "reis": "39",
      "liin": "Tallinn - Viljandi",
      "reisi_algus_aeg": "20:00",
      "reisi_lopp_aeg": "22:05",
      "kiirus": "7",
      "latitude": "58.629034",
      "longitude": "25.561927",
      "rongi_suund": "168",
      "erinevus_plaanist": "1",
      "lisateade": "",
      "pohjus_teade": "",
      "avalda_kodulehel": "",
      "asukoha_uuendus": "2026-05-31 21:42:33",
      "reisi_staatus": "plaaniline",
      "viimane_peatus": "Ollepa"
    },
    {
      "reis": "449",
      "liin": "Tapa - Tallinn",
      "reisi_algus_aeg": "21:24",
      "reisi_lopp_aeg": "22:40",
      "kiirus": "70",
      "latitude": "59.277567",
      "longitude": "25.634766",
      "rongi_suund": "304",
      "erinevus_plaanist": "",
      "lisateade": "",
      "pohjus_teade": "",
      "avalda_kodulehel": "",
      "asukoha_uuendus": "2026-05-31 21:42:34",
      "reisi_staatus": "plaaniline",
      "viimane_peatus": "Nelijärve"
    },
    {
      "reis": "478",
      "liin": "Tallinn - Aegviidu",
      "reisi_algus_aeg": "21:40",
      "reisi_lopp_aeg": "22:35",
      "kiirus": "35",
      "latitude": "59.432736",
      "longitude": "24.722991",
      "rongi_suund": "182",
      "erinevus_plaanist": "",
      "lisateade": "",
      "pohjus_teade": "",
      "avalda_kodulehel": "",
      "asukoha_uuendus": "2026-05-31 21:42:32",
      "reisi_staatus": "plaaniline",
      "viimane_peatus": "Tallinn"
    },
    {
      "reis": "570",
      "liin": "Paldiski - Tallinn",
      "reisi_algus_aeg": "21:00",
      "reisi_lopp_aeg": "21:54",
      "kiirus": "40",
      "latitude": "59.386384",
      "longitude": "24.688287",
      "rongi_suund": "73",
      "erinevus_plaanist": "",
      "lisateade": "",
      "pohjus_teade": "",
      "avalda_kodulehel": "",
      "asukoha_uuendus": "2026-05-31 21:42:32",
      "reisi_staatus": "plaaniline",
      "viimane_peatus": "Nõmme"
    },
    {
      "reis": "572",
      "liin": "Paldiski - Tallinn",
      "reisi_algus_aeg": "22:00",
      "reisi_lopp_aeg": "22:54",
      "kiirus": "0",
      "latitude": "59.344031",
      "longitude": "24.061353",
      "rongi_suund": "316",
      "erinevus_plaanist": "",
      "lisateade": "",
      "pohjus_teade": "",
      "avalda_kodulehel": "",
      "asukoha_uuendus": "2026-05-31 21:42:33",
      "reisi_staatus": "plaaniline",
      "viimane_peatus": "Paldiski"
    },
    {
      "reis": "573",
      "liin": "Tallinn - Paldiski",
      "reisi_algus_aeg": "21:45",
      "reisi_lopp_aeg": "22:39",
      "kiirus": "0",
      "latitude": "59.440222",
      "longitude": "24.736682",
      "rongi_suund": "58",
      "erinevus_plaanist": "",
      "lisateade": "",
      "pohjus_teade": "",
      "avalda_kodulehel": "",
      "asukoha_uuendus": "2026-05-31 21:42:34",
      "reisi_staatus": "plaaniline",
      "viimane_peatus": "Tallinn"
    },
    {
      "reis": "669",
      "liin": "Tallinn - Turba",
      "reisi_algus_aeg": "21:15",
      "reisi_lopp_aeg": "22:18",
      "kiirus": "51",
      "latitude": "59.325492",
      "longitude": "24.549898",
      "rongi_suund": "242",
      "erinevus_plaanist": "",
      "lisateade": "",
      "pohjus_teade": "",
      "avalda_kodulehel": "",
      "asukoha_uuendus": "2026-05-31 21:42:32",
      "reisi_staatus": "plaaniline",
      "viimane_peatus": "Padula"
    },
    {
      "reis": "670",
      "liin": "Turba - Tallinn",
      "reisi_algus_aeg": "21:24",
      "reisi_lopp_aeg": "22:24",
      "kiirus": "106",
      "latitude": "59.247591",
      "longitude": "24.307150",
      "rongi_suund": "24",
      "erinevus_plaanist": "",
      "lisateade": "",
      "pohjus_teade": "",
      "avalda_kodulehel": "",
      "asukoha_uuendus": "2026-05-31 21:42:33",
      "reisi_staatus": "plaaniline",
      "viimane_peatus": "Vasalemma"
    },
    {
      "reis": "92",
      "liin": "Tallinn - Tartu",
      "reisi_algus_aeg": "21:10",
      "reisi_lopp_aeg": "23:15",
      "kiirus": "131",
      "latitude": "59.293298",
      "longitude": "25.483472",
      "rongi_suund": "112",
      "erinevus_plaanist": "",
      "lisateade": "",
      "pohjus_teade": "",
      "avalda_kodulehel": "",
      "asukoha_uuendus": "2026-05-31 21:40:52",
      "reisi_staatus": "plaaniline",
      "viimane_peatus": "Ülemiste"
    }
  ]
}