{
  "fetched_at": "2026-05-28T12:40:46.851246",
  "source": "https://elron.ee/map_data.json",
  "count": 23,
  "trains": [
    {
      "reis": "127",
      "liin": "Koidula - Tartu",
      "reisi_algus_aeg": "15:42",
      "reisi_lopp_aeg": "17:05",
      "kiirus": "0",
      "latitude": "57.836999",
      "longitude": "27.575256",
      "rongi_suund": "82",
      "erinevus_plaanist": "",
      "lisateade": "",
      "pohjus_teade": "",
      "avalda_kodulehel": "",
      "asukoha_uuendus": "2026-05-28 15:40:44",
      "reisi_staatus": "plaaniline",
      "viimane_peatus": "Koidula"
    },
    {
      "reis": "14",
      "liin": "Tallinn - Tartu",
      "reisi_algus_aeg": "13:47",
      "reisi_lopp_aeg": "16:01",
      "kiirus": "121",
      "latitude": "58.568797",
      "longitude": "26.584067",
      "rongi_suund": "162",
      "erinevus_plaanist": "",
      "lisateade": "",
      "pohjus_teade": "",
      "avalda_kodulehel": "",
      "asukoha_uuendus": "2026-05-28 15:40:43",
      "reisi_staatus": "plaaniline",
      "viimane_peatus": "Jõgeva"
    },
    {
      "reis": "15",
      "liin": "Tartu-Tallinn",
      "reisi_algus_aeg": "14:04",
      "reisi_lopp_aeg": "16:11",
      "kiirus": "114",
      "latitude": "59.299089",
      "longitude": "25.462215",
      "rongi_suund": "300",
      "erinevus_plaanist": "",
      "lisateade": "",
      "pohjus_teade": "",
      "avalda_kodulehel": "",
      "asukoha_uuendus": "2026-05-28 15:40:43",
      "reisi_staatus": "plaaniline",
      "viimane_peatus": "Tapa"
    },
    {
      "reis": "16",
      "liin": "Tallinn - Valga / Riia",
      "reisi_algus_aeg": "14:48",
      "reisi_lopp_aeg": "18:32",
      "kiirus": "0",
      "latitude": "59.265529",
      "longitude": "25.961936",
      "rongi_suund": "80",
      "erinevus_plaanist": "",
      "lisateade": "",
      "pohjus_teade": "",
      "avalda_kodulehel": "",
      "asukoha_uuendus": "2026-05-28 15:40:45",
      "reisi_staatus": "plaaniline",
      "viimane_peatus": "Tapa"
    },
    {
      "reis": "17",
      "liin": "Tartu-Tallinn",
      "reisi_algus_aeg": "15:43",
      "reisi_lopp_aeg": "18:01",
      "kiirus": "0",
      "latitude": "58.373681",
      "longitude": "26.706636",
      "rongi_suund": "321",
      "erinevus_plaanist": "",
      "lisateade": "",
      "pohjus_teade": "",
      "avalda_kodulehel": "",
      "asukoha_uuendus": "2026-05-28 15:40:44",
      "reisi_staatus": "plaaniline",
      "viimane_peatus": "Tartu"
    },
    {
      "reis": "222",
      "liin": "Tallinn - Narva",
      "reisi_algus_aeg": "13:09",
      "reisi_lopp_aeg": "16:02",
      "kiirus": "115",
      "latitude": "59.362231",
      "longitude": "27.854287",
      "rongi_suund": "104",
      "erinevus_plaanist": "",
      "lisateade": "",
      "pohjus_teade": "",
      "avalda_kodulehel": "",
      "asukoha_uuendus": "2026-05-28 15:40:45",
      "reisi_staatus": "plaaniline",
      "viimane_peatus": "Vaivara"
    },
    {
      "reis": "225",
      "liin": "Narva - Tallinn",
      "reisi_algus_aeg": "14:38",
      "reisi_lopp_aeg": "17:33",
      "kiirus": "81",
      "latitude": "59.357104",
      "longitude": "27.025531",
      "rongi_suund": "260",
      "erinevus_plaanist": "",
      "lisateade": "",
      "pohjus_teade": "",
      "avalda_kodulehel": "",
      "asukoha_uuendus": "2026-05-28 15:40:45",
      "reisi_staatus": "plaaniline",
      "viimane_peatus": "Püssi"
    },
    {
      "reis": "314",
      "liin": "Türi - Tallinn",
      "reisi_algus_aeg": "15:52",
      "reisi_lopp_aeg": "17:23",
      "kiirus": "0",
      "latitude": "58.805048",
      "longitude": "25.423047",
      "rongi_suund": "95",
      "erinevus_plaanist": "",
      "lisateade": "",
      "pohjus_teade": "",
      "avalda_kodulehel": "",
      "asukoha_uuendus": "2026-05-28 15:40:44",
      "reisi_staatus": "plaaniline",
      "viimane_peatus": "Türi"
    },
    {
      "reis": "329",
      "liin": "Tallinn - Rapla",
      "reisi_algus_aeg": "15:25",
      "reisi_lopp_aeg": "16:24",
      "kiirus": "68",
      "latitude": "59.369672",
      "longitude": "24.721278",
      "rongi_suund": "176",
      "erinevus_plaanist": "",
      "lisateade": "",
      "pohjus_teade": "",
      "avalda_kodulehel": "",
      "asukoha_uuendus": "2026-05-28 15:40:45",
      "reisi_staatus": "plaaniline",
      "viimane_peatus": "Valdeku"
    },
    {
      "reis": "330",
      "liin": "Rapla - Tallinn",
      "reisi_algus_aeg": "15:25",
      "reisi_lopp_aeg": "16:24",
      "kiirus": "80",
      "latitude": "59.128226",
      "longitude": "24.777234",
      "rongi_suund": "338",
      "erinevus_plaanist": "1",
      "lisateade": "",
      "pohjus_teade": "",
      "avalda_kodulehel": "",
      "asukoha_uuendus": "2026-05-28 15:40:43",
      "reisi_staatus": "plaaniline",
      "viimane_peatus": "Lohu"
    },
    {
      "reis": "445",
      "liin": "Tapa - Tallinn",
      "reisi_algus_aeg": "14:24",
      "reisi_lopp_aeg": "15:40",
      "kiirus": "33",
      "latitude": "59.438481",
      "longitude": "24.731898",
      "rongi_suund": "58",
      "erinevus_plaanist": "1",
      "lisateade": "",
      "pohjus_teade": "",
      "avalda_kodulehel": "",
      "asukoha_uuendus": "2026-05-28 15:40:46",
      "reisi_staatus": "plaaniline",
      "viimane_peatus": "Kitseküla"
    },
    {
      "reis": "446",
      "liin": "Tallinn - Tapa",
      "reisi_algus_aeg": "15:29",
      "reisi_lopp_aeg": "16:45",
      "kiirus": "35",
      "latitude": "59.423484",
      "longitude": "24.801649",
      "rongi_suund": "91",
      "erinevus_plaanist": "2",
      "lisateade": "",
      "pohjus_teade": "",
      "avalda_kodulehel": "",
      "asukoha_uuendus": "2026-05-28 15:40:45",
      "reisi_staatus": "hilineb peatuses",
      "viimane_peatus": "Ülemiste"
    },
    {
      "reis": "470",
      "liin": "Tallinn - Aegviidu",
      "reisi_algus_aeg": "15:55",
      "reisi_lopp_aeg": "16:50",
      "kiirus": "0",
      "latitude": "59.439440",
      "longitude": "24.735540",
      "rongi_suund": "58",
      "erinevus_plaanist": "",
      "lisateade": "",
      "pohjus_teade": "",
      "avalda_kodulehel": "",
      "asukoha_uuendus": "2026-05-28 15:40:43",
      "reisi_staatus": "plaaniline",
      "viimane_peatus": "Tallinn"
    },
    {
      "reis": "475",
      "liin": "Aegviidu - Tallinn",
      "reisi_algus_aeg": "16:00",
      "reisi_lopp_aeg": "16:55",
      "kiirus": "0",
      "latitude": "59.285113",
      "longitude": "25.613157",
      "rongi_suund": "124",
      "erinevus_plaanist": "",
      "lisateade": "",
      "pohjus_teade": "",
      "avalda_kodulehel": "",
      "asukoha_uuendus": "2026-05-28 15:40:45",
      "reisi_staatus": "plaaniline",
      "viimane_peatus": "Aegviidu"
    },
    {
      "reis": "558",
      "liin": "Paldiski - Tallinn",
      "reisi_algus_aeg": "15:00",
      "reisi_lopp_aeg": "15:54",
      "kiirus": "0",
      "latitude": "59.383049",
      "longitude": "24.670551",
      "rongi_suund": "64",
      "erinevus_plaanist": "",
      "lisateade": "",
      "pohjus_teade": "",
      "avalda_kodulehel": "",
      "asukoha_uuendus": "2026-05-28 15:40:44",
      "reisi_staatus": "plaaniline",
      "viimane_peatus": "Hiiu"
    },
    {
      "reis": "559",
      "liin": "Tallinn - Paldiski",
      "reisi_algus_aeg": "14:45",
      "reisi_lopp_aeg": "15:40",
      "kiirus": "32",
      "latitude": "59.342075",
      "longitude": "24.064780",
      "rongi_suund": "317",
      "erinevus_plaanist": "1",
      "lisateade": "",
      "pohjus_teade": "",
      "avalda_kodulehel": "",
      "asukoha_uuendus": "2026-05-28 15:40:44",
      "reisi_staatus": "plaaniline",
      "viimane_peatus": "Laoküla"
    },
    {
      "reis": "561",
      "liin": "Tallinn - Paldiski",
      "reisi_algus_aeg": "15:45",
      "reisi_lopp_aeg": "16:40",
      "kiirus": "0",
      "latitude": "59.440303",
      "longitude": "24.736562",
      "rongi_suund": "58",
      "erinevus_plaanist": "",
      "lisateade": "",
      "pohjus_teade": "",
      "avalda_kodulehel": "",
      "asukoha_uuendus": "2026-05-28 15:40:44",
      "reisi_staatus": "plaaniline",
      "viimane_peatus": "Tallinn"
    },
    {
      "reis": "585",
      "liin": "Tallinn - Kloogaranna",
      "reisi_algus_aeg": "15:25",
      "reisi_lopp_aeg": "16:11",
      "kiirus": "35",
      "latitude": "59.382607",
      "longitude": "24.669046",
      "rongi_suund": "238",
      "erinevus_plaanist": "1",
      "lisateade": "",
      "pohjus_teade": "",
      "avalda_kodulehel": "",
      "asukoha_uuendus": "2026-05-28 15:40:46",
      "reisi_staatus": "plaaniline",
      "viimane_peatus": "Hiiu"
    },
    {
      "reis": "657",
      "liin": "Tallinn - Turba",
      "reisi_algus_aeg": "15:05",
      "reisi_lopp_aeg": "16:08",
      "kiirus": "0",
      "latitude": "59.306199",
      "longitude": "24.416545",
      "rongi_suund": "269",
      "erinevus_plaanist": "",
      "lisateade": "",
      "pohjus_teade": "",
      "avalda_kodulehel": "",
      "asukoha_uuendus": "2026-05-28 15:40:45",
      "reisi_staatus": "plaaniline",
      "viimane_peatus": "Keila"
    },
    {
      "reis": "658",
      "liin": "Turba - Tallinn",
      "reisi_algus_aeg": "15:32",
      "reisi_lopp_aeg": "16:34",
      "kiirus": "109",
      "latitude": "59.171344",
      "longitude": "24.319311",
      "rongi_suund": "4",
      "erinevus_plaanist": "",
      "lisateade": "",
      "pohjus_teade": "",
      "avalda_kodulehel": "",
      "asukoha_uuendus": "2026-05-28 15:40:44",
      "reisi_staatus": "plaaniline",
      "viimane_peatus": "Riisipere"
    },
    {
      "reis": "756",
      "liin": "Keila - Tallinn",
      "reisi_algus_aeg": "15:40",
      "reisi_lopp_aeg": "16:14",
      "kiirus": "40",
      "latitude": "59.306093",
      "longitude": "24.418561",
      "rongi_suund": "89",
      "erinevus_plaanist": "",
      "lisateade": "",
      "pohjus_teade": "",
      "avalda_kodulehel": "",
      "asukoha_uuendus": "2026-05-28 15:40:45",
      "reisi_staatus": "plaaniline",
      "viimane_peatus": "Keila"
    },
    {
      "reis": "776",
      "liin": "Pääsküla - Tallinn",
      "reisi_algus_aeg": "15:46",
      "reisi_lopp_aeg": "16:04",
      "kiirus": "0",
      "latitude": "59.369284",
      "longitude": "24.640797",
      "rongi_suund": "46",
      "erinevus_plaanist": "",
      "lisateade": "",
      "pohjus_teade": "",
      "avalda_kodulehel": "",
      "asukoha_uuendus": "2026-05-28 15:40:44",
      "reisi_staatus": "plaaniline",
      "viimane_peatus": "Pääsküla"
    },
    {
      "reis": "9916",
      "liin": "Tallinn - Tartu RV",
      "reisi_algus_aeg": "14:48",
      "reisi_lopp_aeg": "16:55",
      "kiirus": "0",
      "latitude": "59.265473",
      "longitude": "25.961133",
      "rongi_suund": "81",
      "erinevus_plaanist": "",
      "lisateade": "",
      "pohjus_teade": "",
      "avalda_kodulehel": "",
      "asukoha_uuendus": "2026-05-28 15:40:45",
      "reisi_staatus": "plaaniline",
      "viimane_peatus": "Tapa"
    }
  ]
}