{
  "fetched_at": "2026-05-28T16:21:51.601295",
  "source": "https://elron.ee/map_data.json",
  "count": 17,
  "trains": [
    {
      "reis": "105",
      "liin": "Tartu-Tallinn",
      "reisi_algus_aeg": "18:28",
      "reisi_lopp_aeg": "21:02",
      "kiirus": "87",
      "latitude": "58.995247",
      "longitude": "26.242136",
      "rongi_suund": "356",
      "erinevus_plaanist": "",
      "lisateade": "",
      "pohjus_teade": "",
      "avalda_kodulehel": "",
      "asukoha_uuendus": "2026-05-28 19:21:48",
      "reisi_staatus": "plaaniline",
      "viimane_peatus": "Rakke"
    },
    {
      "reis": "18",
      "liin": "Tallinn - Tartu",
      "reisi_algus_aeg": "18:04",
      "reisi_lopp_aeg": "20:21",
      "kiirus": "37",
      "latitude": "59.161139",
      "longitude": "26.109625",
      "rongi_suund": "138",
      "erinevus_plaanist": "",
      "lisateade": "",
      "pohjus_teade": "",
      "avalda_kodulehel": "",
      "asukoha_uuendus": "2026-05-28 19:21:49",
      "reisi_staatus": "plaaniline",
      "viimane_peatus": "Tapa"
    },
    {
      "reis": "19",
      "liin": "Tartu-Tallinn",
      "reisi_algus_aeg": "19:40",
      "reisi_lopp_aeg": "21:49",
      "kiirus": "0",
      "latitude": "58.373601",
      "longitude": "26.706637",
      "rongi_suund": "142",
      "erinevus_plaanist": "",
      "lisateade": "",
      "pohjus_teade": "",
      "avalda_kodulehel": "",
      "asukoha_uuendus": "2026-05-28 19:21:50",
      "reisi_staatus": "plaaniline",
      "viimane_peatus": "Tartu"
    },
    {
      "reis": "227",
      "liin": "Narva - Tallinn",
      "reisi_algus_aeg": "17:27",
      "reisi_lopp_aeg": "20:34",
      "kiirus": "69",
      "latitude": "59.271346",
      "longitude": "25.983608",
      "rongi_suund": "225",
      "erinevus_plaanist": "1",
      "lisateade": "",
      "pohjus_teade": "",
      "avalda_kodulehel": "",
      "asukoha_uuendus": "2026-05-28 19:21:49",
      "reisi_staatus": "plaaniline",
      "viimane_peatus": "Kadrina"
    },
    {
      "reis": "301",
      "liin": "Tallinn - Viljandi",
      "reisi_algus_aeg": "17:24",
      "reisi_lopp_aeg": "19:39",
      "kiirus": "88",
      "latitude": "58.569628",
      "longitude": "25.552311",
      "rongi_suund": "185",
      "erinevus_plaanist": "",
      "lisateade": "",
      "pohjus_teade": "",
      "avalda_kodulehel": "",
      "asukoha_uuendus": "2026-05-28 19:21:48",
      "reisi_staatus": "plaaniline",
      "viimane_peatus": "Võhma"
    },
    {
      "reis": "313",
      "liin": "Tallinn - Türi",
      "reisi_algus_aeg": "18:54",
      "reisi_lopp_aeg": "20:27",
      "kiirus": "69",
      "latitude": "59.257587",
      "longitude": "24.686855",
      "rongi_suund": "167",
      "erinevus_plaanist": "",
      "lisateade": "",
      "pohjus_teade": "",
      "avalda_kodulehel": "",
      "asukoha_uuendus": "2026-05-28 19:21:49",
      "reisi_staatus": "plaaniline",
      "viimane_peatus": "Kasemetsa"
    },
    {
      "reis": "447",
      "liin": "Tapa - Tallinn",
      "reisi_algus_aeg": "18:35",
      "reisi_lopp_aeg": "19:51",
      "kiirus": "13",
      "latitude": "59.371969",
      "longitude": "25.080680",
      "rongi_suund": "273",
      "erinevus_plaanist": "",
      "lisateade": "",
      "pohjus_teade": "",
      "avalda_kodulehel": "",
      "asukoha_uuendus": "2026-05-28 19:21:50",
      "reisi_staatus": "plaaniline",
      "viimane_peatus": "Raasiku"
    },
    {
      "reis": "448",
      "liin": "Tallinn - Tapa",
      "reisi_algus_aeg": "19:06",
      "reisi_lopp_aeg": "20:22",
      "kiirus": "86",
      "latitude": "59.413909",
      "longitude": "24.903939",
      "rongi_suund": "135",
      "erinevus_plaanist": "1",
      "lisateade": "",
      "pohjus_teade": "",
      "avalda_kodulehel": "",
      "asukoha_uuendus": "2026-05-28 19:21:50",
      "reisi_staatus": "plaaniline",
      "viimane_peatus": "Vesse"
    },
    {
      "reis": "476",
      "liin": "Tallinn - Aegviidu",
      "reisi_algus_aeg": "18:28",
      "reisi_lopp_aeg": "19:23",
      "kiirus": "120",
      "latitude": "59.290669",
      "longitude": "25.547790",
      "rongi_suund": "95",
      "erinevus_plaanist": "",
      "lisateade": "",
      "pohjus_teade": "",
      "avalda_kodulehel": "",
      "asukoha_uuendus": "2026-05-28 19:21:50",
      "reisi_staatus": "plaaniline",
      "viimane_peatus": "Mustjõe"
    },
    {
      "reis": "566",
      "liin": "Paldiski - Tallinn",
      "reisi_algus_aeg": "19:00",
      "reisi_lopp_aeg": "19:54",
      "kiirus": "115",
      "latitude": "59.310153",
      "longitude": "24.455330",
      "rongi_suund": "85",
      "erinevus_plaanist": "",
      "lisateade": "",
      "pohjus_teade": "",
      "avalda_kodulehel": "",
      "asukoha_uuendus": "2026-05-28 19:21:50",
      "reisi_staatus": "plaaniline",
      "viimane_peatus": "Keila"
    },
    {
      "reis": "567",
      "liin": "Tallinn - Paldiski",
      "reisi_algus_aeg": "18:45",
      "reisi_lopp_aeg": "19:39",
      "kiirus": "120",
      "latitude": "59.308426",
      "longitude": "24.375342",
      "rongi_suund": "281",
      "erinevus_plaanist": "",
      "lisateade": "",
      "pohjus_teade": "",
      "avalda_kodulehel": "",
      "asukoha_uuendus": "2026-05-28 19:21:48",
      "reisi_staatus": "plaaniline",
      "viimane_peatus": "Keila"
    },
    {
      "reis": "664",
      "liin": "Turba - Tallinn",
      "reisi_algus_aeg": "18:32",
      "reisi_lopp_aeg": "19:34",
      "kiirus": "43",
      "latitude": "59.385676",
      "longitude": "24.683887",
      "rongi_suund": "73",
      "erinevus_plaanist": "",
      "lisateade": "",
      "pohjus_teade": "",
      "avalda_kodulehel": "",
      "asukoha_uuendus": "2026-05-28 19:21:48",
      "reisi_staatus": "plaaniline",
      "viimane_peatus": "Hiiu"
    },
    {
      "reis": "665",
      "liin": "Tallinn - Turba",
      "reisi_algus_aeg": "19:05",
      "reisi_lopp_aeg": "20:07",
      "kiirus": "0",
      "latitude": "59.377317",
      "longitude": "24.657124",
      "rongi_suund": "223",
      "erinevus_plaanist": "",
      "lisateade": "",
      "pohjus_teade": "",
      "avalda_kodulehel": "",
      "asukoha_uuendus": "2026-05-28 19:21:49",
      "reisi_staatus": "plaaniline",
      "viimane_peatus": "Kivimäe"
    },
    {
      "reis": "666",
      "liin": "Turba - Tallinn",
      "reisi_algus_aeg": "19:32",
      "reisi_lopp_aeg": "20:34",
      "kiirus": "0",
      "latitude": "59.076337",
      "longitude": "24.241271",
      "rongi_suund": "243",
      "erinevus_plaanist": "",
      "lisateade": "",
      "pohjus_teade": "",
      "avalda_kodulehel": "",
      "asukoha_uuendus": "2026-05-28 19:21:50",
      "reisi_staatus": "plaaniline",
      "viimane_peatus": "Turba"
    },
    {
      "reis": "711",
      "liin": "Valga - Riia",
      "reisi_algus_aeg": "18:41",
      "reisi_lopp_aeg": "20:46",
      "kiirus": "94",
      "latitude": "57.433885",
      "longitude": "25.443925",
      "rongi_suund": "188",
      "erinevus_plaanist": "1",
      "lisateade": "",
      "pohjus_teade": "",
      "avalda_kodulehel": "",
      "asukoha_uuendus": "2026-05-28 19:21:49",
      "reisi_staatus": "plaaniline",
      "viimane_peatus": "Valmiera"
    },
    {
      "reis": "759",
      "liin": "Tallinn - Keila",
      "reisi_algus_aeg": "19:25",
      "reisi_lopp_aeg": "19:59",
      "kiirus": "0",
      "latitude": "59.440172",
      "longitude": "24.736296",
      "rongi_suund": "58",
      "erinevus_plaanist": "",
      "lisateade": "",
      "pohjus_teade": "",
      "avalda_kodulehel": "",
      "asukoha_uuendus": "2026-05-28 19:21:48",
      "reisi_staatus": "plaaniline",
      "viimane_peatus": "Tallinn"
    },
    {
      "reis": "760",
      "liin": "Keila - Tallinn",
      "reisi_algus_aeg": "19:40",
      "reisi_lopp_aeg": "20:14",
      "kiirus": "0",
      "latitude": "59.306040",
      "longitude": "24.415887",
      "rongi_suund": "269",
      "erinevus_plaanist": "",
      "lisateade": "",
      "pohjus_teade": "",
      "avalda_kodulehel": "",
      "asukoha_uuendus": "2026-05-28 19:21:49",
      "reisi_staatus": "plaaniline",
      "viimane_peatus": "Keila"
    },
    {
      "reis": "93",
      "liin": "Tartu-Tallinn",
      "reisi_algus_aeg": "17:14",
      "reisi_lopp_aeg": "19:21",
      "kiirus": "16",
      "latitude": "59.439328",
      "longitude": "24.734982",
      "rongi_suund": "58",
      "erinevus_plaanist": "",
      "lisateade": "",
      "pohjus_teade": "",
      "avalda_kodulehel": "",
      "asukoha_uuendus": "2026-05-28 19:21:48",
      "reisi_staatus": "plaaniline",
      "viimane_peatus": "Kitseküla"
    }
  ]
}