{
  "fetched_at": "2026-05-28T17:28:51.597673",
  "source": "https://elron.ee/map_data.json",
  "count": 14,
  "trains": [
    {
      "reis": "105",
      "liin": "Tartu-Tallinn",
      "reisi_algus_aeg": "18:28",
      "reisi_lopp_aeg": "21:02",
      "kiirus": "104",
      "latitude": "59.329038",
      "longitude": "25.361414",
      "rongi_suund": "300",
      "erinevus_plaanist": "",
      "lisateade": "",
      "pohjus_teade": "",
      "avalda_kodulehel": "",
      "asukoha_uuendus": "2026-05-28 20:28:49",
      "reisi_staatus": "plaaniline",
      "viimane_peatus": "Aegviidu"
    },
    {
      "reis": "106",
      "liin": "Tallinn - Tartu",
      "reisi_algus_aeg": "19:55",
      "reisi_lopp_aeg": "22:28",
      "kiirus": "99",
      "latitude": "59.330250",
      "longitude": "25.357185",
      "rongi_suund": "120",
      "erinevus_plaanist": "",
      "lisateade": "",
      "pohjus_teade": "",
      "avalda_kodulehel": "",
      "asukoha_uuendus": "2026-05-28 20:28:48",
      "reisi_staatus": "plaaniline",
      "viimane_peatus": "Kehra"
    },
    {
      "reis": "118",
      "liin": "Tartu-Valga",
      "reisi_algus_aeg": "20:22",
      "reisi_lopp_aeg": "22:02",
      "kiirus": "50",
      "latitude": "58.354881",
      "longitude": "26.709579",
      "rongi_suund": "227",
      "erinevus_plaanist": "1",
      "lisateade": "",
      "pohjus_teade": "",
      "avalda_kodulehel": "",
      "asukoha_uuendus": "2026-05-28 20:28:49",
      "reisi_staatus": "plaaniline",
      "viimane_peatus": "Aardla"
    },
    {
      "reis": "19",
      "liin": "Tartu-Tallinn",
      "reisi_algus_aeg": "19:40",
      "reisi_lopp_aeg": "21:49",
      "kiirus": "120",
      "latitude": "59.074503",
      "longitude": "26.188571",
      "rongi_suund": "335",
      "erinevus_plaanist": "1",
      "lisateade": "",
      "pohjus_teade": "",
      "avalda_kodulehel": "",
      "asukoha_uuendus": "2026-05-28 20:28:46",
      "reisi_staatus": "plaaniline",
      "viimane_peatus": "Jõgeva"
    },
    {
      "reis": "227",
      "liin": "Narva - Tallinn",
      "reisi_algus_aeg": "17:27",
      "reisi_lopp_aeg": "20:34",
      "kiirus": "79",
      "latitude": "59.416913",
      "longitude": "24.751901",
      "rongi_suund": "274",
      "erinevus_plaanist": "",
      "lisateade": "",
      "pohjus_teade": "",
      "avalda_kodulehel": "",
      "asukoha_uuendus": "2026-05-28 20:28:50",
      "reisi_staatus": "plaaniline",
      "viimane_peatus": "Ülemiste"
    },
    {
      "reis": "38",
      "liin": "Viljandi - Tallinn",
      "reisi_algus_aeg": "20:03",
      "reisi_lopp_aeg": "22:09",
      "kiirus": "94",
      "latitude": "58.642166",
      "longitude": "25.555729",
      "rongi_suund": "344",
      "erinevus_plaanist": "1",
      "lisateade": "",
      "pohjus_teade": "",
      "avalda_kodulehel": "",
      "asukoha_uuendus": "2026-05-28 20:28:49",
      "reisi_staatus": "plaaniline",
      "viimane_peatus": "Võhma"
    },
    {
      "reis": "39",
      "liin": "Tallinn - Viljandi",
      "reisi_algus_aeg": "20:00",
      "reisi_lopp_aeg": "22:05",
      "kiirus": "100",
      "latitude": "59.213091",
      "longitude": "24.701915",
      "rongi_suund": "163",
      "erinevus_plaanist": "",
      "lisateade": "",
      "pohjus_teade": "",
      "avalda_kodulehel": "",
      "asukoha_uuendus": "2026-05-28 20:28:48",
      "reisi_staatus": "plaaniline",
      "viimane_peatus": "Kiisa"
    },
    {
      "reis": "450",
      "liin": "Tallinn - Tapa",
      "reisi_algus_aeg": "20:20",
      "reisi_lopp_aeg": "21:36",
      "kiirus": "8",
      "latitude": "59.423508",
      "longitude": "24.797607",
      "rongi_suund": "90",
      "erinevus_plaanist": "",
      "lisateade": "",
      "pohjus_teade": "",
      "avalda_kodulehel": "",
      "asukoha_uuendus": "2026-05-28 20:28:50",
      "reisi_staatus": "plaaniline",
      "viimane_peatus": "Ülemiste"
    },
    {
      "reis": "479",
      "liin": "Aegviidu - Tallinn",
      "reisi_algus_aeg": "20:25",
      "reisi_lopp_aeg": "21:20",
      "kiirus": "119",
      "latitude": "59.291600",
      "longitude": "25.527053",
      "rongi_suund": "275",
      "erinevus_plaanist": "",
      "lisateade": "",
      "pohjus_teade": "",
      "avalda_kodulehel": "",
      "asukoha_uuendus": "2026-05-28 20:28:48",
      "reisi_staatus": "plaaniline",
      "viimane_peatus": "Aegviidu"
    },
    {
      "reis": "568",
      "liin": "Paldiski - Tallinn",
      "reisi_algus_aeg": "20:00",
      "reisi_lopp_aeg": "20:54",
      "kiirus": "107",
      "latitude": "59.339331",
      "longitude": "24.597729",
      "rongi_suund": "60",
      "erinevus_plaanist": "",
      "lisateade": "",
      "pohjus_teade": "",
      "avalda_kodulehel": "",
      "asukoha_uuendus": "2026-05-28 20:28:49",
      "reisi_staatus": "plaaniline",
      "viimane_peatus": "Saue"
    },
    {
      "reis": "569",
      "liin": "Tallinn - Paldiski",
      "reisi_algus_aeg": "19:45",
      "reisi_lopp_aeg": "20:39",
      "kiirus": "41",
      "latitude": "59.321184",
      "longitude": "24.251145",
      "rongi_suund": "277",
      "erinevus_plaanist": "",
      "lisateade": "",
      "pohjus_teade": "",
      "avalda_kodulehel": "",
      "asukoha_uuendus": "2026-05-28 20:28:49",
      "reisi_staatus": "plaaniline",
      "viimane_peatus": "Klooga"
    },
    {
      "reis": "666",
      "liin": "Turba - Tallinn",
      "reisi_algus_aeg": "19:32",
      "reisi_lopp_aeg": "20:34",
      "kiirus": "0",
      "latitude": "59.410806",
      "longitude": "24.733471",
      "rongi_suund": "15",
      "erinevus_plaanist": "",
      "lisateade": "",
      "pohjus_teade": "",
      "avalda_kodulehel": "",
      "asukoha_uuendus": "2026-05-28 20:28:48",
      "reisi_staatus": "plaaniline",
      "viimane_peatus": "Tondi"
    },
    {
      "reis": "667",
      "liin": "Tallinn - Turba",
      "reisi_algus_aeg": "20:15",
      "reisi_lopp_aeg": "21:15",
      "kiirus": "67",
      "latitude": "59.384396",
      "longitude": "24.675815",
      "rongi_suund": "248",
      "erinevus_plaanist": "",
      "lisateade": "",
      "pohjus_teade": "",
      "avalda_kodulehel": "",
      "asukoha_uuendus": "2026-05-28 20:28:48",
      "reisi_staatus": "plaaniline",
      "viimane_peatus": "Nõmme"
    },
    {
      "reis": "668",
      "liin": "Turba - Tallinn",
      "reisi_algus_aeg": "20:22",
      "reisi_lopp_aeg": "21:24",
      "kiirus": "115",
      "latitude": "59.129272",
      "longitude": "24.313541",
      "rongi_suund": "4",
      "erinevus_plaanist": "",
      "lisateade": "",
      "pohjus_teade": "",
      "avalda_kodulehel": "",
      "asukoha_uuendus": "2026-05-28 20:28:49",
      "reisi_staatus": "plaaniline",
      "viimane_peatus": "Riisipere"
    },
    {
      "reis": "711",
      "liin": "Valga - Riia",
      "reisi_algus_aeg": "18:41",
      "reisi_lopp_aeg": "20:46",
      "kiirus": "112",
      "latitude": "57.013890",
      "longitude": "24.309733",
      "rongi_suund": "240",
      "erinevus_plaanist": "2",
      "lisateade": "",
      "pohjus_teade": "",
      "avalda_kodulehel": "",
      "asukoha_uuendus": "2026-05-28 20:28:48",
      "reisi_staatus": "hilineb peatuses",
      "viimane_peatus": "Sigulda"
    }
  ]
}