{
  "fetched_at": "2026-05-28T07:33:48.304072",
  "source": "https://elron.ee/map_data.json",
  "count": 21,
  "trains": [
    {
      "reis": "10",
      "liin": "Tallinn - Tartu",
      "reisi_algus_aeg": "08:30",
      "reisi_lopp_aeg": "10:38",
      "kiirus": "111",
      "latitude": "58.401067",
      "longitude": "26.677399",
      "rongi_suund": "159",
      "erinevus_plaanist": "1",
      "lisateade": "",
      "pohjus_teade": "",
      "avalda_kodulehel": "",
      "asukoha_uuendus": "2026-05-28 10:33:47",
      "reisi_staatus": "plaaniline",
      "viimane_peatus": "Jõgeva"
    },
    {
      "reis": "12",
      "liin": "Tallinn - Tartu",
      "reisi_algus_aeg": "10:51",
      "reisi_lopp_aeg": "13:00",
      "kiirus": "0",
      "latitude": "59.440102",
      "longitude": "24.736677",
      "rongi_suund": "",
      "erinevus_plaanist": "",
      "lisateade": "",
      "pohjus_teade": "",
      "avalda_kodulehel": "",
      "asukoha_uuendus": "2026-05-28 10:33:46",
      "reisi_staatus": "plaaniline",
      "viimane_peatus": "Tallinn"
    },
    {
      "reis": "122",
      "liin": "Tartu - Koidula",
      "reisi_algus_aeg": "10:45",
      "reisi_lopp_aeg": "12:09",
      "kiirus": "0",
      "latitude": "58.374252",
      "longitude": "26.705540",
      "rongi_suund": "319",
      "erinevus_plaanist": "",
      "lisateade": "",
      "pohjus_teade": "",
      "avalda_kodulehel": "",
      "asukoha_uuendus": "2026-05-28 10:33:45",
      "reisi_staatus": "plaaniline",
      "viimane_peatus": "Tartu"
    },
    {
      "reis": "13",
      "liin": "Riia / Valga - Tallinn",
      "reisi_algus_aeg": "09:40",
      "reisi_lopp_aeg": "13:18",
      "kiirus": "51",
      "latitude": "58.211167",
      "longitude": "26.413295",
      "rongi_suund": "19",
      "erinevus_plaanist": "1",
      "lisateade": "",
      "pohjus_teade": "",
      "avalda_kodulehel": "",
      "asukoha_uuendus": "2026-05-28 10:33:47",
      "reisi_staatus": "plaaniline",
      "viimane_peatus": "Palupera"
    },
    {
      "reis": "20",
      "liin": "Tallinn - Narva",
      "reisi_algus_aeg": "09:55",
      "reisi_lopp_aeg": "12:36",
      "kiirus": "68",
      "latitude": "59.267637",
      "longitude": "25.657406",
      "rongi_suund": "139",
      "erinevus_plaanist": "1",
      "lisateade": "",
      "pohjus_teade": "",
      "avalda_kodulehel": "",
      "asukoha_uuendus": "2026-05-28 10:33:45",
      "reisi_staatus": "plaaniline",
      "viimane_peatus": "Ülemiste"
    },
    {
      "reis": "21",
      "liin": "Narva - Tallinn",
      "reisi_algus_aeg": "09:55",
      "reisi_lopp_aeg": "12:25",
      "kiirus": "46",
      "latitude": "59.356155",
      "longitude": "27.387151",
      "rongi_suund": "273",
      "erinevus_plaanist": "",
      "lisateade": "",
      "pohjus_teade": "",
      "avalda_kodulehel": "",
      "asukoha_uuendus": "2026-05-28 10:33:46",
      "reisi_staatus": "plaaniline",
      "viimane_peatus": "Jõhvi"
    },
    {
      "reis": "32",
      "liin": "Viljandi - Tallinn",
      "reisi_algus_aeg": "10:03",
      "reisi_lopp_aeg": "12:06",
      "kiirus": "105",
      "latitude": "58.715016",
      "longitude": "25.524571",
      "rongi_suund": "360",
      "erinevus_plaanist": "",
      "lisateade": "",
      "pohjus_teade": "",
      "avalda_kodulehel": "",
      "asukoha_uuendus": "2026-05-28 10:33:47",
      "reisi_staatus": "plaaniline",
      "viimane_peatus": "Ollepa"
    },
    {
      "reis": "326",
      "liin": "Rapla - Tallinn",
      "reisi_algus_aeg": "10:12",
      "reisi_lopp_aeg": "11:11",
      "kiirus": "57",
      "latitude": "59.178040",
      "longitude": "24.736504",
      "rongi_suund": "333",
      "erinevus_plaanist": "",
      "lisateade": "",
      "pohjus_teade": "",
      "avalda_kodulehel": "",
      "asukoha_uuendus": "2026-05-28 10:33:45",
      "reisi_staatus": "plaaniline",
      "viimane_peatus": "Kohila"
    },
    {
      "reis": "33",
      "liin": "Tallinn - Viljandi",
      "reisi_algus_aeg": "09:59",
      "reisi_lopp_aeg": "12:05",
      "kiirus": "82",
      "latitude": "59.160062",
      "longitude": "24.752449",
      "rongi_suund": "158",
      "erinevus_plaanist": "",
      "lisateade": "",
      "pohjus_teade": "",
      "avalda_kodulehel": "",
      "asukoha_uuendus": "2026-05-28 10:33:46",
      "reisi_staatus": "plaaniline",
      "viimane_peatus": "Kohila"
    },
    {
      "reis": "443",
      "liin": "Tapa - Tallinn",
      "reisi_algus_aeg": "10:34",
      "reisi_lopp_aeg": "11:50",
      "kiirus": "0",
      "latitude": "59.265379",
      "longitude": "25.961356",
      "rongi_suund": "81",
      "erinevus_plaanist": "",
      "lisateade": "",
      "pohjus_teade": "",
      "avalda_kodulehel": "",
      "asukoha_uuendus": "2026-05-28 10:33:48",
      "reisi_staatus": "plaaniline",
      "viimane_peatus": "Tapa"
    },
    {
      "reis": "464",
      "liin": "Tallinn - Aegviidu",
      "reisi_algus_aeg": "10:25",
      "reisi_lopp_aeg": "11:20",
      "kiirus": "0",
      "latitude": "59.423487",
      "longitude": "24.797989",
      "rongi_suund": "80",
      "erinevus_plaanist": "",
      "lisateade": "",
      "pohjus_teade": "",
      "avalda_kodulehel": "",
      "asukoha_uuendus": "2026-05-28 10:33:46",
      "reisi_staatus": "plaaniline",
      "viimane_peatus": "Ülemiste"
    },
    {
      "reis": "469",
      "liin": "Aegviidu - Tallinn",
      "reisi_algus_aeg": "09:45",
      "reisi_lopp_aeg": "10:40",
      "kiirus": "89",
      "latitude": "59.423052",
      "longitude": "24.778800",
      "rongi_suund": "252",
      "erinevus_plaanist": "",
      "lisateade": "",
      "pohjus_teade": "",
      "avalda_kodulehel": "",
      "asukoha_uuendus": "2026-05-28 10:33:45",
      "reisi_staatus": "plaaniline",
      "viimane_peatus": "Ülemiste"
    },
    {
      "reis": "548",
      "liin": "Paldiski - Tallinn",
      "reisi_algus_aeg": "10:00",
      "reisi_lopp_aeg": "10:54",
      "kiirus": "0",
      "latitude": "59.354603",
      "longitude": "24.627774",
      "rongi_suund": "8",
      "erinevus_plaanist": "",
      "lisateade": "",
      "pohjus_teade": "",
      "avalda_kodulehel": "",
      "asukoha_uuendus": "2026-05-28 10:33:46",
      "reisi_staatus": "plaaniline",
      "viimane_peatus": "Laagri"
    },
    {
      "reis": "549",
      "liin": "Tallinn - Paldiski",
      "reisi_algus_aeg": "09:45",
      "reisi_lopp_aeg": "10:39",
      "kiirus": "80",
      "latitude": "59.328007",
      "longitude": "24.184015",
      "rongi_suund": "282",
      "erinevus_plaanist": "1",
      "lisateade": "",
      "pohjus_teade": "",
      "avalda_kodulehel": "",
      "asukoha_uuendus": "2026-05-28 10:33:47",
      "reisi_staatus": "plaaniline",
      "viimane_peatus": "Klooga-Aedlinn"
    },
    {
      "reis": "581",
      "liin": "Tallinn - Kloogaranna",
      "reisi_algus_aeg": "10:25",
      "reisi_lopp_aeg": "11:11",
      "kiirus": "48",
      "latitude": "59.399026",
      "longitude": "24.723198",
      "rongi_suund": "206",
      "erinevus_plaanist": "",
      "lisateade": "",
      "pohjus_teade": "",
      "avalda_kodulehel": "",
      "asukoha_uuendus": "2026-05-28 10:33:48",
      "reisi_staatus": "plaaniline",
      "viimane_peatus": "Järve"
    },
    {
      "reis": "646",
      "liin": "Turba - Tallinn",
      "reisi_algus_aeg": "09:32",
      "reisi_lopp_aeg": "10:34",
      "kiirus": "36",
      "latitude": "59.437842",
      "longitude": "24.729611",
      "rongi_suund": "57",
      "erinevus_plaanist": "",
      "lisateade": "",
      "pohjus_teade": "",
      "avalda_kodulehel": "",
      "asukoha_uuendus": "2026-05-28 10:33:46",
      "reisi_staatus": "plaaniline",
      "viimane_peatus": "Lilleküla"
    },
    {
      "reis": "647",
      "liin": "Tallinn - Turba",
      "reisi_algus_aeg": "10:05",
      "reisi_lopp_aeg": "11:07",
      "kiirus": "0",
      "latitude": "59.324805",
      "longitude": "24.547466",
      "rongi_suund": "241",
      "erinevus_plaanist": "",
      "lisateade": "",
      "pohjus_teade": "",
      "avalda_kodulehel": "",
      "asukoha_uuendus": "2026-05-28 10:33:46",
      "reisi_staatus": "plaaniline",
      "viimane_peatus": "Saue"
    },
    {
      "reis": "648",
      "liin": "Turba - Tallinn",
      "reisi_algus_aeg": "10:32",
      "reisi_lopp_aeg": "11:34",
      "kiirus": "103",
      "latitude": "59.083963",
      "longitude": "24.264299",
      "rongi_suund": "43",
      "erinevus_plaanist": "",
      "lisateade": "",
      "pohjus_teade": "",
      "avalda_kodulehel": "",
      "asukoha_uuendus": "2026-05-28 10:33:47",
      "reisi_staatus": "plaaniline",
      "viimane_peatus": "Turba"
    },
    {
      "reis": "750",
      "liin": "Keila - Tallinn",
      "reisi_algus_aeg": "10:40",
      "reisi_lopp_aeg": "11:14",
      "kiirus": "0",
      "latitude": "59.306050",
      "longitude": "24.416014",
      "rongi_suund": "268",
      "erinevus_plaanist": "",
      "lisateade": "",
      "pohjus_teade": "",
      "avalda_kodulehel": "",
      "asukoha_uuendus": "2026-05-28 10:33:46",
      "reisi_staatus": "plaaniline",
      "viimane_peatus": "Keila"
    },
    {
      "reis": "90",
      "liin": "Tallinn - Tartu",
      "reisi_algus_aeg": "09:55",
      "reisi_lopp_aeg": "12:02",
      "kiirus": "67",
      "latitude": "59.267462",
      "longitude": "25.657697",
      "rongi_suund": "139",
      "erinevus_plaanist": "1",
      "lisateade": "",
      "pohjus_teade": "",
      "avalda_kodulehel": "",
      "asukoha_uuendus": "2026-05-28 10:33:44",
      "reisi_staatus": "plaaniline",
      "viimane_peatus": "Ülemiste"
    },
    {
      "reis": "91",
      "liin": "Tartu-Tallinn",
      "reisi_algus_aeg": "08:59",
      "reisi_lopp_aeg": "11:07",
      "kiirus": "40",
      "latitude": "59.265594",
      "longitude": "25.972608",
      "rongi_suund": "292",
      "erinevus_plaanist": "13",
      "lisateade": ".",
      "pohjus_teade": "koosseisurikke tõttu",
      "avalda_kodulehel": "1",
      "asukoha_uuendus": "2026-05-28 10:33:45",
      "reisi_staatus": "hilineb",
      "viimane_peatus": "teadmata"
    }
  ]
}