{
  "fetched_at": "2026-05-28T12:33:46.850405",
  "source": "https://elron.ee/map_data.json",
  "count": 20,
  "trains": [
    {
      "reis": "117",
      "liin": "Valga - Tartu",
      "reisi_algus_aeg": "14:33",
      "reisi_lopp_aeg": "15:40",
      "kiirus": "112",
      "latitude": "58.344955",
      "longitude": "26.689471",
      "rongi_suund": "47",
      "erinevus_plaanist": "",
      "lisateade": "",
      "pohjus_teade": "",
      "avalda_kodulehel": "",
      "asukoha_uuendus": "2026-05-28 15:33:44",
      "reisi_staatus": "plaaniline",
      "viimane_peatus": "Elva"
    },
    {
      "reis": "134",
      "liin": "Piusa - Koidula",
      "reisi_algus_aeg": "15:27",
      "reisi_lopp_aeg": "15:35",
      "kiirus": "43",
      "latitude": "57.836258",
      "longitude": "27.561558",
      "rongi_suund": "85",
      "erinevus_plaanist": "",
      "lisateade": "",
      "pohjus_teade": "",
      "avalda_kodulehel": "",
      "asukoha_uuendus": "2026-05-28 15:33:44",
      "reisi_staatus": "plaaniline",
      "viimane_peatus": "Piusa"
    },
    {
      "reis": "14",
      "liin": "Tallinn - Tartu",
      "reisi_algus_aeg": "13:47",
      "reisi_lopp_aeg": "16:01",
      "kiirus": "116",
      "latitude": "58.677860",
      "longitude": "26.488732",
      "rongi_suund": "135",
      "erinevus_plaanist": "",
      "lisateade": "",
      "pohjus_teade": "",
      "avalda_kodulehel": "",
      "asukoha_uuendus": "2026-05-28 15:33:45",
      "reisi_staatus": "plaaniline",
      "viimane_peatus": "Jõgeva"
    },
    {
      "reis": "15",
      "liin": "Tartu-Tallinn",
      "reisi_algus_aeg": "14:04",
      "reisi_lopp_aeg": "16:11",
      "kiirus": "84",
      "latitude": "59.266861",
      "longitude": "25.658867",
      "rongi_suund": "318",
      "erinevus_plaanist": "",
      "lisateade": "",
      "pohjus_teade": "",
      "avalda_kodulehel": "",
      "asukoha_uuendus": "2026-05-28 15:33:45",
      "reisi_staatus": "plaaniline",
      "viimane_peatus": "Tapa"
    },
    {
      "reis": "16",
      "liin": "Tallinn - Valga / Riia",
      "reisi_algus_aeg": "14:48",
      "reisi_lopp_aeg": "18:32",
      "kiirus": "72",
      "latitude": "59.254986",
      "longitude": "25.831965",
      "rongi_suund": "81",
      "erinevus_plaanist": "1",
      "lisateade": "",
      "pohjus_teade": "",
      "avalda_kodulehel": "",
      "asukoha_uuendus": "2026-05-28 15:33:45",
      "reisi_staatus": "plaaniline",
      "viimane_peatus": "Ülemiste"
    },
    {
      "reis": "225",
      "liin": "Narva - Tallinn",
      "reisi_algus_aeg": "14:38",
      "reisi_lopp_aeg": "17:33",
      "kiirus": "102",
      "latitude": "59.359726",
      "longitude": "27.136160",
      "rongi_suund": "269",
      "erinevus_plaanist": "",
      "lisateade": "",
      "pohjus_teade": "",
      "avalda_kodulehel": "",
      "asukoha_uuendus": "2026-05-28 15:33:45",
      "reisi_staatus": "plaaniline",
      "viimane_peatus": "Kohtla-Nõmme"
    },
    {
      "reis": "314",
      "liin": "Türi - Tallinn",
      "reisi_algus_aeg": "15:52",
      "reisi_lopp_aeg": "17:23",
      "kiirus": "0",
      "latitude": "58.805040",
      "longitude": "25.423036",
      "rongi_suund": "95",
      "erinevus_plaanist": "",
      "lisateade": "",
      "pohjus_teade": "",
      "avalda_kodulehel": "",
      "asukoha_uuendus": "2026-05-28 15:33:44",
      "reisi_staatus": "plaaniline",
      "viimane_peatus": "Türi"
    },
    {
      "reis": "329",
      "liin": "Tallinn - Rapla",
      "reisi_algus_aeg": "15:25",
      "reisi_lopp_aeg": "16:24",
      "kiirus": "44",
      "latitude": "59.405623",
      "longitude": "24.737747",
      "rongi_suund": "215",
      "erinevus_plaanist": "",
      "lisateade": "",
      "pohjus_teade": "",
      "avalda_kodulehel": "",
      "asukoha_uuendus": "2026-05-28 15:33:45",
      "reisi_staatus": "plaaniline",
      "viimane_peatus": "Tallinn-Väike"
    },
    {
      "reis": "330",
      "liin": "Rapla - Tallinn",
      "reisi_algus_aeg": "15:25",
      "reisi_lopp_aeg": "16:24",
      "kiirus": "20",
      "latitude": "59.065750",
      "longitude": "24.812507",
      "rongi_suund": "303",
      "erinevus_plaanist": "1",
      "lisateade": "",
      "pohjus_teade": "",
      "avalda_kodulehel": "",
      "asukoha_uuendus": "2026-05-28 15:33:45",
      "reisi_staatus": "plaaniline",
      "viimane_peatus": "Hagudi"
    },
    {
      "reis": "445",
      "liin": "Tapa - Tallinn",
      "reisi_algus_aeg": "14:24",
      "reisi_lopp_aeg": "15:40",
      "kiirus": "58",
      "latitude": "59.423402",
      "longitude": "24.791229",
      "rongi_suund": "266",
      "erinevus_plaanist": "",
      "lisateade": "",
      "pohjus_teade": "",
      "avalda_kodulehel": "",
      "asukoha_uuendus": "2026-05-28 15:33:46",
      "reisi_staatus": "plaaniline",
      "viimane_peatus": "Ülemiste"
    },
    {
      "reis": "446",
      "liin": "Tallinn - Tapa",
      "reisi_algus_aeg": "15:29",
      "reisi_lopp_aeg": "16:45",
      "kiirus": "67",
      "latitude": "59.424501",
      "longitude": "24.728930",
      "rongi_suund": "145",
      "erinevus_plaanist": "1",
      "lisateade": "",
      "pohjus_teade": "",
      "avalda_kodulehel": "",
      "asukoha_uuendus": "2026-05-28 15:33:46",
      "reisi_staatus": "plaaniline",
      "viimane_peatus": "Tallinn"
    },
    {
      "reis": "558",
      "liin": "Paldiski - Tallinn",
      "reisi_algus_aeg": "15:00",
      "reisi_lopp_aeg": "15:54",
      "kiirus": "19",
      "latitude": "59.354857",
      "longitude": "24.627856",
      "rongi_suund": "7",
      "erinevus_plaanist": "",
      "lisateade": "",
      "pohjus_teade": "",
      "avalda_kodulehel": "",
      "asukoha_uuendus": "2026-05-28 15:33:44",
      "reisi_staatus": "plaaniline",
      "viimane_peatus": "Laagri"
    },
    {
      "reis": "559",
      "liin": "Tallinn - Paldiski",
      "reisi_algus_aeg": "14:45",
      "reisi_lopp_aeg": "15:40",
      "kiirus": "117",
      "latitude": "59.327195",
      "longitude": "24.192146",
      "rongi_suund": "281",
      "erinevus_plaanist": "1",
      "lisateade": "",
      "pohjus_teade": "",
      "avalda_kodulehel": "",
      "asukoha_uuendus": "2026-05-28 15:33:44",
      "reisi_staatus": "plaaniline",
      "viimane_peatus": "Klooga-Aedlinn"
    },
    {
      "reis": "561",
      "liin": "Tallinn - Paldiski",
      "reisi_algus_aeg": "15:45",
      "reisi_lopp_aeg": "16:40",
      "kiirus": "0",
      "latitude": "59.440308",
      "longitude": "24.736570",
      "rongi_suund": "58",
      "erinevus_plaanist": "",
      "lisateade": "",
      "pohjus_teade": "",
      "avalda_kodulehel": "",
      "asukoha_uuendus": "2026-05-28 15:33:44",
      "reisi_staatus": "plaaniline",
      "viimane_peatus": "Tallinn"
    },
    {
      "reis": "585",
      "liin": "Tallinn - Kloogaranna",
      "reisi_algus_aeg": "15:25",
      "reisi_lopp_aeg": "16:11",
      "kiirus": "16",
      "latitude": "59.400441",
      "longitude": "24.724466",
      "rongi_suund": "203",
      "erinevus_plaanist": "",
      "lisateade": "",
      "pohjus_teade": "",
      "avalda_kodulehel": "",
      "asukoha_uuendus": "2026-05-28 15:33:46",
      "reisi_staatus": "plaaniline",
      "viimane_peatus": "Järve"
    },
    {
      "reis": "656",
      "liin": "Turba - Tallinn",
      "reisi_algus_aeg": "14:32",
      "reisi_lopp_aeg": "15:34",
      "kiirus": "35",
      "latitude": "59.437991",
      "longitude": "24.730012",
      "rongi_suund": "58",
      "erinevus_plaanist": "",
      "lisateade": "",
      "pohjus_teade": "",
      "avalda_kodulehel": "",
      "asukoha_uuendus": "2026-05-28 15:33:44",
      "reisi_staatus": "plaaniline",
      "viimane_peatus": "Lilleküla"
    },
    {
      "reis": "657",
      "liin": "Tallinn - Turba",
      "reisi_algus_aeg": "15:05",
      "reisi_lopp_aeg": "16:08",
      "kiirus": "0",
      "latitude": "59.324806",
      "longitude": "24.547371",
      "rongi_suund": "244",
      "erinevus_plaanist": "",
      "lisateade": "",
      "pohjus_teade": "",
      "avalda_kodulehel": "",
      "asukoha_uuendus": "2026-05-28 15:33:45",
      "reisi_staatus": "plaaniline",
      "viimane_peatus": "Saue"
    },
    {
      "reis": "658",
      "liin": "Turba - Tallinn",
      "reisi_algus_aeg": "15:32",
      "reisi_lopp_aeg": "16:34",
      "kiirus": "120",
      "latitude": "59.086027",
      "longitude": "24.267643",
      "rongi_suund": "39",
      "erinevus_plaanist": "",
      "lisateade": "",
      "pohjus_teade": "",
      "avalda_kodulehel": "",
      "asukoha_uuendus": "2026-05-28 15:33:44",
      "reisi_staatus": "plaaniline",
      "viimane_peatus": "Turba"
    },
    {
      "reis": "756",
      "liin": "Keila - Tallinn",
      "reisi_algus_aeg": "15:40",
      "reisi_lopp_aeg": "16:14",
      "kiirus": "0",
      "latitude": "59.306087",
      "longitude": "24.415922",
      "rongi_suund": "267",
      "erinevus_plaanist": "",
      "lisateade": "",
      "pohjus_teade": "",
      "avalda_kodulehel": "",
      "asukoha_uuendus": "2026-05-28 15:33:45",
      "reisi_staatus": "plaaniline",
      "viimane_peatus": "Keila"
    },
    {
      "reis": "9916",
      "liin": "Tallinn - Tartu RV",
      "reisi_algus_aeg": "14:48",
      "reisi_lopp_aeg": "16:55",
      "kiirus": "72",
      "latitude": "59.254946",
      "longitude": "25.831157",
      "rongi_suund": "81",
      "erinevus_plaanist": "",
      "lisateade": "",
      "pohjus_teade": "",
      "avalda_kodulehel": "",
      "asukoha_uuendus": "2026-05-28 15:33:45",
      "reisi_staatus": "plaaniline",
      "viimane_peatus": "Ülemiste"
    }
  ]
}